tracelogging.py
tracelogging-0.1.5.dist-info/LICENSE
tracelogging-0.1.5.dist-info/METADATA
tracelogging-0.1.5.dist-info/WHEEL
tracelogging-0.1.5.dist-info/top_level.txt
tracelogging-0.1.5.dist-info/RECORD
