Metadata-Version: 2.1
Name: tracelogging
Version: 0.1.5
Summary: python tracelogging for windows
Home-page: https://github.com/bnbdr/tracelogging
Author: bnbdr
Author-email: bad.32@outlook.com
License: MIT
Keywords: windows tracelogging python etw trace
Platform: UNKNOWN
Classifier: Intended Audience :: Developers
Classifier: Programming Language :: Python :: 3
Classifier: License :: OSI Approved :: MIT License
Classifier: Operating System :: Microsoft :: Windows
